<?xml version="1.0" encoding="UTF-8" standalone="yes"?><GameModeTypes xmlns:xsi="http://www.w3.org/2001/XMLSchema-instance"><GameModeType GameModeName="XLTemplate"><GameModeID>0</GameModeID><DisplayNameKey>Must be a valid entry in stringTable.xml</DisplayNameKey><Teams>FALSE</Teams><MaxPlayers>4</MaxPlayers><Duration>240</Duration><RoundDuration>0</RoundDuration><StartingLives>0</StartingLives><ScoringType>TIMED</ScoringType><ScoreToWin>0</ScoreToWin><FixedCamera>false</FixedCamera><LevelSet>StandardAll</LevelSet><CompetitiveLevelSet>Tournament1v1</CompetitiveLevelSet><GameSpeed>1</GameSpeed><GadgetsOff>FALSE</GadgetsOff><WeaponsOff>FALSE</WeaponsOff><DamageRatio>1</DamageRatio><Tournament>FALSE</Tournament><Event>FALSE</Event><TeamDamage>FALSE</TeamDamage><TrainingIcon>--</TrainingIcon><TestFeaturesOn>FALSE</TestFeaturesOn><TestLevelsOn>FALSE</TestLevelsOn><GhostRule>FALSE</GhostRule><DescriptionKey>Must be a valid entry in stringTable.xml</DescriptionKey></GameModeType><GameModeType GameModeName="DefaultTimed"><GameModeID>1</GameModeID><DisplayNameKey>GameModeType_DefaultTimed_DisplayName</DisplayNameKey><Teams>FALSE</Teams><MaxPlayers>4</MaxPlayers><Duration>240</Duration><StartingLives>0</StartingLives><ScoringType>TIMED</ScoringType></GameModeType><GameModeType GameModeName="DefaultStock"><GameModeID>2</GameModeID><DisplayNameKey>GameModeType_DefaultStock_DisplayName</DisplayNameKey><Teams>FALSE</Teams><MaxPlayers>4</MaxPlayers><Duration>480</Duration><StartingLives>3</StartingLives><ScoringType>STOCK</ScoringType></GameModeType><GameModeType GameModeName="Pax"><GameModeID>10</GameModeID><DisplayNameKey>GameModeType_Pax_DisplayName</DisplayNameKey><Teams>FALSE</Teams><MaxPlayers>4</MaxPlayers><Duration>180</Duration><StartingLives>0</StartingLives><ScoringType>TIMED</ScoringType><LevelSet>Pax</LevelSet></GameModeType><GameModeType GameModeName="Endless"><GameModeID>11</GameModeID><DisplayNameKey>GameModeType_Endless_DisplayName</DisplayNameKey><Teams>FALSE</Teams><MaxPlayers>4</MaxPlayers><Duration>0</Duration><StartingLives>0</StartingLives><ScoringType>TIMED</ScoringType><LevelSet>StandardFFA</LevelSet></GameModeType><GameModeType GameModeName="TrainingMode"><GameModeID>12</GameModeID><DisplayNameKey>GameModeType_TrainingMode_DisplayName</DisplayNameKey><Teams>FALSE</Teams><MaxPlayers>2</MaxPlayers><Duration>0</Duration><StartingLives>0</StartingLives><ScoringType>TIMED</ScoringType><LevelSet>StandardAll</LevelSet><TrainingIcon>a_TrainingIcon_Training</TrainingIcon></GameModeType><GameModeType GameModeName="TournamentStock"><GameModeID>19</GameModeID><DisplayNameKey>GameModeType_TournamentStock_DisplayName</DisplayNameKey><Teams>FALSE</Teams><MaxPlayers>4</MaxPlayers><Duration>0</Duration><StartingLives>3</StartingLives><ScoringType>STOCK</ScoringType><LevelSet>StandardFFA</LevelSet><Tournament>TRUE</Tournament></GameModeType><GameModeType GameModeName="DefaultBombsketball"><GameModeID>21</GameModeID><DisplayNameKey>GameModeType_DefaultBombsketball_DisplayName</DisplayNameKey><Teams>TRUE</Teams><MaxPlayers>4</MaxPlayers><Duration>120</Duration><StartingLives>0</StartingLives><ScoringType>BOMBSKETBALL</ScoringType><FixedCamera>true</FixedCamera><GadgetsOff>TRUE</GadgetsOff><WeaponsOff>TRUE</WeaponsOff></GameModeType><GameModeType GameModeName="DefaultConquest"><GameModeID>22</GameModeID><DisplayNameKey>GameModeType_DefaultConquest_DisplayName</DisplayNameKey><Teams>4</Teams><MaxPlayers>4</MaxPlayers><Duration>240</Duration><StartingLives>0</StartingLives><ScoringType>CONQUEST</ScoringType><FixedCamera>false</FixedCamera></GameModeType><GameModeType GameModeName="DefaultHoldTheThing"><GameModeID>23</GameModeID><DisplayNameKey>GameModeType_DefaultHoldTheThing_DisplayName</DisplayNameKey><Teams>FALSE</Teams><MaxPlayers>4</MaxPlayers><Duration>240</Duration><StartingLives>0</StartingLives><ScoringType>HOLDTHETHING</ScoringType></GameModeType><GameModeType GameModeName="DefaultRicochet"><GameModeID>25</GameModeID><DisplayNameKey>GameModeType_DefaultRicochet_DisplayName</DisplayNameKey><Teams>FALSE</Teams><MaxPlayers>4</MaxPlayers><Duration>900</Duration><StartingLives>5</StartingLives><ScoringType>RICOCHET</ScoringType><FixedCamera>true</FixedCamera><GadgetsOff>TRUE</GadgetsOff><WeaponsOff>TRUE</WeaponsOff></GameModeType><GameModeType GameModeName="DefaultBrawlball"><GameModeID>26</GameModeID><DisplayNameKey>GameModeType_DefaultBrawlball_DisplayName</DisplayNameKey><Teams>TRUE</Teams><MaxPlayers>4</MaxPlayers><Duration>900</Duration><RoundDuration>45</RoundDuration><StartingLives>0</StartingLives><ScoringType>BRAWLBALL</ScoringType><ScoreToWin>5</ScoreToWin><GadgetsOff>TRUE</GadgetsOff><WeaponsOff>TRUE</WeaponsOff></GameModeType><GameModeType GameModeName="DefaultDodgeball"><GameModeID>27</GameModeID><DisplayNameKey>GameModeType_DefaultDodgeball_DisplayName</DisplayNameKey><Teams>TRUE</Teams><MaxPlayers>4</MaxPlayers><Duration>240</Duration><StartingLives>3</StartingLives><ScoringType>DODGEBALL</ScoringType><GadgetsOff>TRUE</GadgetsOff><WeaponsOff>TRUE</WeaponsOff></GameModeType><GameModeType GameModeName="DefaultVolleyball"><GameModeID>28</GameModeID><DisplayNameKey>GameModeType_DefaultVolleyball_DisplayName</DisplayNameKey><Teams>TRUE</Teams><MaxPlayers>4</MaxPlayers><Duration>120</Duration><StartingLives>0</StartingLives><ScoringType>VOLLEYBALL</ScoringType><FixedCamera>true</FixedCamera><GadgetsOff>TRUE</GadgetsOff><WeaponsOff>TRUE</WeaponsOff></GameModeType><GameModeType GameModeName="DefaultGauntlet"><GameModeID>29</GameModeID><DisplayNameKey>GameModeType_DefaultGauntlet_DisplayName</DisplayNameKey><Teams>FALSE</Teams><MaxPlayers>4</MaxPlayers><RoundDuration>45</RoundDuration><StartingLives>0</StartingLives><ScoringType>GAUNTLET</ScoringType><GadgetsOff>TRUE</GadgetsOff><WeaponsOff>TRUE</WeaponsOff></GameModeType><GameModeType GameModeName="DefaultHotPotato"><GameModeID>30</GameModeID><DisplayNameKey>GameModeType_DefaultHotPotato_DisplayName</DisplayNameKey><Teams>FALSE</Teams><MaxPlayers>4</MaxPlayers><Duration>120</Duration><StartingLives>0</StartingLives><ScoringType>HOTPOTATO</ScoringType></GameModeType><GameModeType GameModeName="FastForward"><GameModeID>31</GameModeID><DisplayNameKey>GameModeType_FastForward_DisplayName</DisplayNameKey><Teams>FALSE</Teams><MaxPlayers>4</MaxPlayers><Duration>120</Duration><StartingLives>0</StartingLives><ScoringType>TIMED</ScoringType><GameSpeed>1.2</GameSpeed></GameModeType><GameModeType GameModeName="DefaultArcadeSurvival"><GameModeID>33</GameModeID><DisplayNameKey>GameModeType_DefaultArcadeSurvival_DisplayName</DisplayNameKey><Teams>FALSE</Teams><MaxPlayers>4</MaxPlayers><RoundDuration>120</RoundDuration><StartingLives>0</StartingLives><ScoringType>ARCADE</ScoringType></GameModeType><GameModeType GameModeName="DefaultCTF"><GameModeID>34</GameModeID><DisplayNameKey>GameModeType_DefaultCTF_DisplayName</DisplayNameKey><Teams>TRUE</Teams><MaxPlayers>8</MaxPlayers><Duration>480</Duration><StartingLives>0</StartingLives><ScoringType>CTF</ScoringType><ScoreToWin>3</ScoreToWin><FixedCamera>true</FixedCamera><GadgetsOff>TRUE</GadgetsOff><DamageRatio>1</DamageRatio></GameModeType><GameModeType GameModeName="1v1StockRanked"><GameModeID>36</GameModeID><DisplayNameKey>GameModeType_1v1StockRanked_DisplayName</DisplayNameKey><Teams>FALSE</Teams><MaxPlayers>2</MaxPlayers><Duration>480</Duration><StartingLives>3</StartingLives><ScoringType>STOCK</ScoringType><LevelSet>Standard1v1</LevelSet><CompetitiveLevelSet>Tournament1v1</CompetitiveLevelSet></GameModeType><GameModeType GameModeName="4FFACasual"><GameModeID>37</GameModeID><DisplayNameKey>GameModeType_4FFACasual_DisplayName</DisplayNameKey><Teams>FALSE</Teams><MaxPlayers>4</MaxPlayers><Duration>240</Duration><StartingLives>0</StartingLives><ScoringType>TIMED</ScoringType><LevelSet>StandardFFA</LevelSet></GameModeType><GameModeType GameModeName="DefaultHydra"><GameModeID>38</GameModeID><DisplayNameKey>GameModeType_DefaultHydra_DisplayName</DisplayNameKey><Teams>FALSE</Teams><MaxPlayers>8</MaxPlayers><Duration>0</Duration><StartingLives>0</StartingLives><ScoringType>HYDRA</ScoringType></GameModeType><GameModeType GameModeName="TeamStockRanked"><GameModeID>39</GameModeID><DisplayNameKey>GameModeType_TeamStockRanked_DisplayName</DisplayNameKey><Teams>TRUE</Teams><MaxPlayers>4</MaxPlayers><Duration>480</Duration><StartingLives>3</StartingLives><ScoringType>STOCK</ScoringType><LevelSet>Standard2v2</LevelSet><CompetitiveLevelSet>Tournament2v2</CompetitiveLevelSet><TeamDamage>TRUE</TeamDamage></GameModeType><GameModeType GameModeName="DefaultSnowball"><GameModeID>40</GameModeID><DisplayNameKey>GameModeType_DefaultSnowball_DisplayName</DisplayNameKey><Teams>TRUE</Teams><MaxPlayers>8</MaxPlayers><Duration>180</Duration><StartingLives>0</StartingLives><ScoringType>SNOWBALL</ScoringType><GadgetsOff>TRUE</GadgetsOff><WeaponsOff>TRUE</WeaponsOff></GameModeType><GameModeType GameModeName="DefaultRelay"><GameModeID>41</GameModeID><DisplayNameKey>GameModeType_DefaultRelay_DisplayName</DisplayNameKey><Teams>FALSE</Teams><MaxPlayers>8</MaxPlayers><Duration>480</Duration><StartingLives>3</StartingLives><ScoringType>RELAY</ScoringType></GameModeType><GameModeType GameModeName="1v1RelayUnranked"><GameModeID>42</GameModeID><DisplayNameKey>GameModeType_1v1RelayUnranked_DisplayName</DisplayNameKey><Teams>FALSE</Teams><MaxPlayers>2</MaxPlayers><Duration>480</Duration><StartingLives>3</StartingLives><ScoringType>RELAY</ScoringType><LevelSet>Standard1v1</LevelSet></GameModeType><GameModeType GameModeName="DefaultPracticeCatchBombs"><GameModeID>43</GameModeID><DisplayNameKey>GameModeType_DefaultPracticeCatchBombs_DisplayName</DisplayNameKey><Teams>FALSE</Teams><MaxPlayers>1</MaxPlayers><Duration>0</Duration><StartingLives>0</StartingLives><ScoringType>CATCHBOMBS</ScoringType><FixedCamera>true</FixedCamera><LevelSet>PracticeCatchBombs</LevelSet><GadgetsOff>TRUE</GadgetsOff><WeaponsOff>TRUE</WeaponsOff><TrainingIcon>a_TrainingIcon_CatchBombs</TrainingIcon></GameModeType><GameModeType GameModeName="1v1StockExperimental"><GameModeID>44</GameModeID><DisplayNameKey>GameModeType_1v1StockExperimental_DisplayName</DisplayNameKey><Teams>FALSE</Teams><MaxPlayers>2</MaxPlayers><Duration>480</Duration><StartingLives>3</StartingLives><ScoringType>STOCK</ScoringType><LevelSet>Experimental1v1</LevelSet><TestFeaturesOn>TRUE</TestFeaturesOn><TestLevelsOn>TRUE</TestLevelsOn></GameModeType><GameModeType GameModeName="DefaultHockey"><GameModeID>45</GameModeID><DisplayNameKey>GameModeType_DefaultHockey_DisplayName</DisplayNameKey><Teams>TRUE</Teams><MaxPlayers>4</MaxPlayers><Duration>60</Duration><StartingLives>0</StartingLives><ScoringType>HOCKEY</ScoringType><FixedCamera>true</FixedCamera><GadgetsOff>TRUE</GadgetsOff><WeaponsOff>TRUE</WeaponsOff></GameModeType><GameModeType GameModeName="DefaultTauntbrawl"><GameModeID>46</GameModeID><DisplayNameKey>GameModeType_DefaultTauntbrawl_DisplayName</DisplayNameKey><Teams>FALSE</Teams><MaxPlayers>4</MaxPlayers><Duration>120</Duration><StartingLives>0</StartingLives><ScoringType>TAUNTBRAWL</ScoringType></GameModeType><GameModeType GameModeName="DefaultSimon"><GameModeID>57</GameModeID><DisplayNameKey>GameModeType_DefaultSimon_DisplayName</DisplayNameKey><Teams>FALSE</Teams><MaxPlayers>4</MaxPlayers><Duration>0</Duration><StartingLives>1</StartingLives><ScoringType>SIMON</ScoringType><FixedCamera>true</FixedCamera><LevelSet>SimonAll</LevelSet><GadgetsOff>TRUE</GadgetsOff><WeaponsOff>TRUE</WeaponsOff></GameModeType><GameModeType GameModeName="DefaultBountyHunter"><GameModeID>58</GameModeID><DisplayNameKey>GameModeType_DefaultBountyHunter_DisplayName</DisplayNameKey><Teams>FALSE</Teams><MaxPlayers>4</MaxPlayers><Duration>0</Duration><StartingLives>1</StartingLives><ScoringType>BOUNTYHUNTER</ScoringType></GameModeType><GameModeType GameModeName="DefaultScramble"><GameModeID>59</GameModeID><DisplayNameKey>GameModeType_DefaultScramble_DisplayName</DisplayNameKey><Teams>FALSE</Teams><MaxPlayers>4</MaxPlayers><Duration>480</Duration><StartingLives>3</StartingLives><ScoringType>SCRAMBLE</ScoringType></GameModeType><GameModeType GameModeName="DefaultColorPlatforms"><GameModeID>60</GameModeID><DisplayNameKey>GameModeType_DefaultColorPlatforms_DisplayName</DisplayNameKey><Teams>FALSE</Teams><MaxPlayers>4</MaxPlayers><Duration>120</Duration><StartingLives>0</StartingLives><ScoringType>COLORPLATFORMS</ScoringType><FixedCamera>true</FixedCamera><LevelSet>ColorPlatformsAll</LevelSet></GameModeType><GameModeType GameModeName="DefaultPogo"><GameModeID>61</GameModeID><DisplayNameKey>GameModeType_DefaultPogo_DisplayName</DisplayNameKey><Teams>FALSE</Teams><MaxPlayers>4</MaxPlayers><Duration>60</Duration><StartingLives>0</StartingLives><ScoringType>POGO</ScoringType><FixedCamera>true</FixedCamera><LevelSet>PogoAll</LevelSet><GadgetsOff>TRUE</GadgetsOff><WeaponsOff>TRUE</WeaponsOff></GameModeType><GameModeType GameModeName="DefaultSkeebomb"><GameModeID>62</GameModeID><DisplayNameKey>GameModeType_DefaultSkeebomb_DisplayName</DisplayNameKey><Teams>TRUE</Teams><MaxPlayers>4</MaxPlayers><Duration>60</Duration><StartingLives>0</StartingLives><ScoringType>SKEEBOMB</ScoringType><FixedCamera>true</FixedCamera><LevelSet>SkeebombAll</LevelSet><GadgetsOff>TRUE</GadgetsOff><WeaponsOff>TRUE</WeaponsOff><TeamDamage>TRUE</TeamDamage></GameModeType><GameModeType GameModeName="DefaultSuperbrawl"><GameModeID>63</GameModeID><DisplayNameKey>GameModeType_DefaultSuperbrawl_DisplayName</DisplayNameKey><Teams>FALSE</Teams><MaxPlayers>4</MaxPlayers><Duration>120</Duration><StartingLives>0</StartingLives><ScoringType>SUPERBRAWL</ScoringType></GameModeType><GameModeType GameModeName="DefaultBCX1v1"><GameModeID>64</GameModeID><DisplayNameKey>GameModeType_DefaultBCX1v1_DisplayName</DisplayNameKey><Teams>FALSE</Teams><MaxPlayers>2</MaxPlayers><Duration>480</Duration><StartingLives>3</StartingLives><ScoringType>STOCK</ScoringType><LevelSet>Tournament1v1</LevelSet><GadgetsOff>TRUE</GadgetsOff></GameModeType><GameModeType GameModeName="DefaultBCX2v2"><GameModeID>65</GameModeID><DisplayNameKey>GameModeType_DefaultBCX2v2_DisplayName</DisplayNameKey><Teams>TRUE</Teams><MaxPlayers>4</MaxPlayers><Duration>480</Duration><StartingLives>3</StartingLives><ScoringType>STOCK</ScoringType><LevelSet>Tournament2v2</LevelSet><GadgetsOff>TRUE</GadgetsOff><TeamDamage>TRUE</TeamDamage></GameModeType><GameModeType GameModeName="DefaultGiant"><GameModeID>66</GameModeID><DisplayNameKey>GameModeType_DefaultGiant_DisplayName</DisplayNameKey><Teams>FALSE</Teams><MaxPlayers>4</MaxPlayers><Duration>120</Duration><StartingLives>0</StartingLives><ScoringType>GIANT</ScoringType></GameModeType><GameModeType GameModeName="DefaultPartyMode"><GameModeID>67</GameModeID><DisplayNameKey>GameModeType_DefaultPartyMode_DisplayName</DisplayNameKey><Teams>FALSE</Teams><MaxPlayers>4</MaxPlayers><ScoringType>PARTYMODE</ScoringType></GameModeType><GameModeType GameModeName="DefaultKOTH"><GameModeID>68</GameModeID><DisplayNameKey>GameModeType_DefaultKOTH_DisplayName</DisplayNameKey><Teams>FALSE</Teams><MaxPlayers>4</MaxPlayers><Duration>120</Duration><StartingLives>0</StartingLives><ScoringType>KOTH</ScoringType><FixedCamera>true</FixedCamera><LevelSet>KothAll</LevelSet></GameModeType><GameModeType GameModeName="SnowballFFA"><GameModeID>69</GameModeID><DisplayNameKey>GameModeType_SnowballFFA_DisplayName</DisplayNameKey><Teams>FALSE</Teams><MaxPlayers>4</MaxPlayers><Duration>180</Duration><StartingLives>0</StartingLives><ScoringType>SNOWBALL</ScoringType><LevelSet>SnowballFFA</LevelSet><GadgetsOff>TRUE</GadgetsOff><WeaponsOff>TRUE</WeaponsOff></GameModeType><GameModeType GameModeName="Snowball2v2"><GameModeID>70</GameModeID><DisplayNameKey>GameModeType_Snowball2v2_DisplayName</DisplayNameKey><Teams>TRUE</Teams><MaxPlayers>4</MaxPlayers><Duration>180</Duration><StartingLives>0</StartingLives><ScoringType>SNOWBALL</ScoringType><LevelSet>SnowballFFA</LevelSet><GadgetsOff>TRUE</GadgetsOff><WeaponsOff>TRUE</WeaponsOff><TeamDamage>FALSE</TeamDamage></GameModeType><GameModeType GameModeName="Tutorial1"><GameModeID>71</GameModeID><DisplayNameKey>GameModeType_Tutorial1_DisplayName</DisplayNameKey><Teams>FALSE</Teams><MaxPlayers>2</MaxPlayers><Duration>0</Duration><StartingLives>3</StartingLives><ScoringType>STOCK</ScoringType><LevelSet>Tutorial1</LevelSet><GadgetsOff>TRUE</GadgetsOff></GameModeType><GameModeType GameModeName="Tutorial2"><GameModeID>72</GameModeID><DisplayNameKey>GameModeType_Tutorial2_DisplayName</DisplayNameKey><Teams>FALSE</Teams><MaxPlayers>2</MaxPlayers><Duration>0</Duration><StartingLives>3</StartingLives><ScoringType>STOCK</ScoringType><LevelSet>Tutorial2</LevelSet><GadgetsOff>TRUE</GadgetsOff></GameModeType><GameModeType GameModeName="Tutorial3"><GameModeID>73</GameModeID><DisplayNameKey>GameModeType_Tutorial3_DisplayName</DisplayNameKey><Teams>FALSE</Teams><MaxPlayers>4</MaxPlayers><Duration>0</Duration><StartingLives>3</StartingLives><ScoringType>STOCK</ScoringType><LevelSet>Tutorial3</LevelSet><GadgetsOff>FALSE</GadgetsOff></GameModeType><GameModeType GameModeName="Brawlball3v3"><GameModeID>74</GameModeID><DisplayNameKey>GameModeType_Brawlball3v3_DisplayName</DisplayNameKey><Teams>TRUE</Teams><MaxPlayers>6</MaxPlayers><Duration>900</Duration><RoundDuration>45</RoundDuration><StartingLives>0</StartingLives><ScoringType>BRAWLBALL</ScoringType><ScoreToWin>5</ScoreToWin><GadgetsOff>TRUE</GadgetsOff><WeaponsOff>TRUE</WeaponsOff></GameModeType><GameModeType GameModeName="DefaultRicochetTimed"><GameModeID>75</GameModeID><DisplayNameKey>GameModeType_DefaultRicochetTimed_DisplayName</DisplayNameKey><Teams>FALSE</Teams><MaxPlayers>4</MaxPlayers><Duration>120</Duration><StartingLives>0</StartingLives><ScoringType>RICOCHETTIMED</ScoringType><FixedCamera>true</FixedCamera><GadgetsOff>TRUE</GadgetsOff><WeaponsOff>TRUE</WeaponsOff></GameModeType><GameModeType GameModeName="BOTWRicochetTimed"><GameModeID>76</GameModeID><DisplayNameKey>GameModeType_BOTWRicochetTimed_DisplayName</DisplayNameKey><Teams>FALSE</Teams><MaxPlayers>4</MaxPlayers><Duration>120</Duration><StartingLives>0</StartingLives><ScoringType>RICOCHETTIMED</ScoringType><FixedCamera>true</FixedCamera><LevelSet>RicochetFFA</LevelSet><GadgetsOff>TRUE</GadgetsOff><WeaponsOff>TRUE</WeaponsOff><DescriptionKey>GameModeType_BOTWRicochetTimed_DescriptionKey</DescriptionKey></GameModeType><GameModeType GameModeName="BOTW8FFA"><GameModeID>77</GameModeID><DisplayNameKey>GameModeType_BOTW8FFA_DisplayName</DisplayNameKey><Teams>FALSE</Teams><MaxPlayers>8</MaxPlayers><Duration>180</Duration><StartingLives>0</StartingLives><ScoringType>TIMED</ScoringType><LevelSet>StandardBig</LevelSet><DamageRatio>2</DamageRatio><DescriptionKey>GameModeType_BOTW8FFA_DescriptionKey</DescriptionKey></GameModeType><GameModeType GameModeName="BOTW1v1Switch"><GameModeID>78</GameModeID><DisplayNameKey>GameModeType_BOTW1v1Switch_DisplayName</DisplayNameKey><Teams>false</Teams><MaxPlayers>2</MaxPlayers><Duration>480</Duration><StartingLives>3</StartingLives><ScoringType>SCRAMBLE</ScoringType><LevelSet>Standard1v1</LevelSet><DescriptionKey>GameModeType_BOTW1v1Switch_DescriptionKey</DescriptionKey></GameModeType><GameModeType GameModeName="BOTW1v1300"><GameModeID>79</GameModeID><DisplayNameKey>GameModeType_BOTW1v1300_DisplayName</DisplayNameKey><Teams>false</Teams><MaxPlayers>2</MaxPlayers><Duration>480</Duration><StartingLives>5</StartingLives><ScoringType>STOCK</ScoringType><LevelSet>Standard1v1</LevelSet><DamageRatio>3</DamageRatio><DescriptionKey>GameModeType_BOTW1v1300_DescriptionKey</DescriptionKey></GameModeType><GameModeType GameModeName="BOTWSnowbrawl"><GameModeID>80</GameModeID><DisplayNameKey>GameModeType_BOTWSnowbrawl_DisplayName</DisplayNameKey><Teams>false</Teams><MaxPlayers>4</MaxPlayers><Duration>180</Duration><StartingLives>0</StartingLives><ScoringType>SNOWBALL</ScoringType><LevelSet>SnowballFFA</LevelSet><GadgetsOff>true</GadgetsOff><WeaponsOff>true</WeaponsOff><DamageRatio>1.5</DamageRatio><DescriptionKey>GameModeType_BOTWSnowbrawl_DescriptionKey</DescriptionKey></GameModeType><GameModeType GameModeName="BOTW3FFA"><GameModeID>81</GameModeID><DisplayNameKey>GameModeType_BOTW3FFA_DisplayName</DisplayNameKey><Teams>FALSE</Teams><MaxPlayers>3</MaxPlayers><Duration>180</Duration><StartingLives>0</StartingLives><ScoringType>TIMED</ScoringType><LevelSet>Standard1v1</LevelSet><DescriptionKey>GameModeType_BOTW3FFA_DescriptionKey</DescriptionKey></GameModeType><GameModeType GameModeName="BOTWPlatformFight"><GameModeID>82</GameModeID><DisplayNameKey>GameModeType_BOTWPlatformFight_DisplayName</DisplayNameKey><Teams>FALSE</Teams><MaxPlayers>4</MaxPlayers><Duration>120</Duration><StartingLives>0</StartingLives><ScoringType>COLORPLATFORMS</ScoringType><FixedCamera>true</FixedCamera><LevelSet>ColorPlatformsAll</LevelSet><DescriptionKey>GameModeType_BOTWPlatformFight_DescriptionKey</DescriptionKey></GameModeType><GameModeType GameModeName="BOTW4FFASingleLegend"><GameModeID>83</GameModeID><DisplayNameKey>GameModeType_BOTW4FFASingleLegend_DisplayName</DisplayNameKey><Teams>FALSE</Teams><MaxPlayers>4</MaxPlayers><Duration>180</Duration><StartingLives>0</StartingLives><ScoringType>TIMED</ScoringType><LevelSet>StandardFFA</LevelSet><DescriptionKey>GameModeType_BOTW4FFASingleLegend_DescriptionKey</DescriptionKey></GameModeType><GameModeType GameModeName="BOTW2v2"><GameModeID>84</GameModeID><DisplayNameKey>GameModeType_BOTW2v2_DisplayName</DisplayNameKey><Teams>true</Teams><MaxPlayers>4</MaxPlayers><Duration>480</Duration><StartingLives>3</StartingLives><ScoringType>STOCK</ScoringType><LevelSet>Standard2v2</LevelSet><TeamDamage>false</TeamDamage><DescriptionKey>GameModeType_BOTW2v2_DescriptionKey</DescriptionKey></GameModeType><GameModeType GameModeName="BOTW3v3Brawlball"><GameModeID>85</GameModeID><DisplayNameKey>GameModeType_BOTW3v3Brawlball_DisplayName</DisplayNameKey><Teams>true</Teams><MaxPlayers>6</MaxPlayers><Duration>300</Duration><RoundDuration>30</RoundDuration><StartingLives>0</StartingLives><ScoringType>BRAWLBALL</ScoringType><ScoreToWin>3</ScoreToWin><LevelSet>BrawlballBig</LevelSet><GadgetsOff>TRUE</GadgetsOff><WeaponsOff>TRUE</WeaponsOff><DescriptionKey>GameModeType_BOTW3v3Brawlball_DescriptionKey</DescriptionKey></GameModeType><GameModeType GameModeName="BOTW2v2300"><GameModeID>86</GameModeID><DisplayNameKey>GameModeType_BOTW2v2300_DisplayName</DisplayNameKey><Teams>true</Teams><MaxPlayers>4</MaxPlayers><Duration>480</Duration><StartingLives>5</StartingLives><ScoringType>STOCK</ScoringType><LevelSet>Standard2v2</LevelSet><DamageRatio>3</DamageRatio><TeamDamage>false</TeamDamage><DescriptionKey>GameModeType_BOTW2v2300_DescriptionKey</DescriptionKey></GameModeType><GameModeType GameModeName="BOTW3v3Beachbrawl"><GameModeID>87</GameModeID><DisplayNameKey>GameModeType_BOTW3v3Beachbrawl_DisplayName</DisplayNameKey><Teams>TRUE</Teams><MaxPlayers>6</MaxPlayers><Duration>120</Duration><StartingLives>0</StartingLives><ScoringType>VOLLEYBALL</ScoringType><FixedCamera>true</FixedCamera><LevelSet>VolleyballAll</LevelSet><GadgetsOff>TRUE</GadgetsOff><WeaponsOff>TRUE</WeaponsOff><DescriptionKey>GameModeType_BOTW3v3Beachbrawl_DescriptionKey</DescriptionKey></GameModeType><GameModeType GameModeName="BOTWHeatwaveSnowbrawl"><GameModeID>88</GameModeID><DisplayNameKey>GameModeType_BOTWHeatwaveSnowbrawl_DisplayName</DisplayNameKey><Teams>TRUE</Teams><MaxPlayers>6</MaxPlayers><Duration>180</Duration><StartingLives>0</StartingLives><ScoringType>SNOWBALL</ScoringType><LevelSet>Standard2v2</LevelSet><GadgetsOff>true</GadgetsOff><WeaponsOff>true</WeaponsOff><DamageRatio>1.5</DamageRatio><DescriptionKey>GameModeType_BOTWHeatwaveSnowbrawl_DescriptionKey</DescriptionKey></GameModeType><GameModeType GameModeName="BOTWHeatwaveFFA"><GameModeID>89</GameModeID><DisplayNameKey>GameModeType_BOTWHeatwaveFFA_DisplayName</DisplayNameKey><Teams>FALSE</Teams><MaxPlayers>6</MaxPlayers><Duration>180</Duration><StartingLives>0</StartingLives><ScoringType>TIMEDWATERBOMB</ScoringType><LevelSet>StandardFFA</LevelSet><DamageRatio>2</DamageRatio><DescriptionKey>GameModeType_BOTWHeatwaveFFA_DescriptionKey</DescriptionKey></GameModeType><GameModeType GameModeName="BOTW2v2PlatformFight"><GameModeID>90</GameModeID><DisplayNameKey>GameModeType_BOTW2v2PlatformFight_DisplayName</DisplayNameKey><Teams>true</Teams><MaxPlayers>4</MaxPlayers><Duration>120</Duration><StartingLives>0</StartingLives><ScoringType>COLORPLATFORMS</ScoringType><FixedCamera>true</FixedCamera><LevelSet>ColorPlatformsAll</LevelSet><DescriptionKey>GameModeType_BOTW2v2PlatformFight_DescriptionKey</DescriptionKey></GameModeType><GameModeType GameModeName="Unranked2v2"><GameModeID>91</GameModeID><DisplayNameKey>GameModeType_Unranked2v2_DisplayName</DisplayNameKey><Teams>true</Teams><MaxPlayers>4</MaxPlayers><Duration>480</Duration><StartingLives>3</StartingLives><ScoringType>STOCK</ScoringType><LevelSet>Standard2v2</LevelSet><TeamDamage>false</TeamDamage></GameModeType><GameModeType GameModeName="HauntedFloors"><GameModeID>92</GameModeID><DisplayNameKey>GameModeType_HauntedFloors_DisplayName</DisplayNameKey><Teams>FALSE</Teams><MaxPlayers>4</MaxPlayers><Duration>180</Duration><StartingLives>0</StartingLives><ScoringType>HAUNTEDFLOORS</ScoringType><DescriptionKey>GameModeType_HauntedFloors_DescriptionKey</DescriptionKey></GameModeType><GameModeType GameModeName="BOTW2v2Relay"><GameModeID>93</GameModeID><DisplayNameKey>GameModeType_BOTW2v2Relay_DisplayName</DisplayNameKey><Teams>true</Teams><MaxPlayers>4</MaxPlayers><Duration>480</Duration><StartingLives>3</StartingLives><ScoringType>RELAY</ScoringType><LevelSet>Standard2v2</LevelSet><TeamDamage>false</TeamDamage><DescriptionKey>GameModeType_BOTW2v2Relay_DescriptionKey</DescriptionKey></GameModeType><GameModeType GameModeName="BOTW3v3"><GameModeID>94</GameModeID><DisplayNameKey>GameModeType_BOTW3v3_DisplayName</DisplayNameKey><Teams>true</Teams><MaxPlayers>6</MaxPlayers><Duration>480</Duration><StartingLives>3</StartingLives><ScoringType>STOCK</ScoringType><LevelSet>Standard3v3</LevelSet><TeamDamage>false</TeamDamage><DescriptionKey>GameModeType_BOTW3v3_DescriptionKey</DescriptionKey></GameModeType><GameModeType GameModeName="BOTW2v2Switch"><GameModeID>95</GameModeID><DisplayNameKey>GameModeType_BOTW2v2Switch_DisplayName</DisplayNameKey><Teams>true</Teams><MaxPlayers>4</MaxPlayers><Duration>480</Duration><StartingLives>3</StartingLives><ScoringType>SCRAMBLE</ScoringType><LevelSet>Standard2v2</LevelSet><TeamDamage>false</TeamDamage><DescriptionKey>GameModeType_BOTW2v2Switch_DescriptionKey</DescriptionKey></GameModeType><GameModeType GameModeName="BOTW2v2Snowbrawl"><GameModeID>96</GameModeID><DisplayNameKey>GameModeType_BOTW2v2Snowbrawl_DisplayName</DisplayNameKey><Teams>true</Teams><MaxPlayers>4</MaxPlayers><Duration>180</Duration><StartingLives>0</StartingLives><ScoringType>SNOWBALL</ScoringType><LevelSet>SnowballFFA</LevelSet><GadgetsOff>true</GadgetsOff><WeaponsOff>true</WeaponsOff><DamageRatio>1.5</DamageRatio><DescriptionKey>GameModeType_BOTW2v2Snowbrawl_DescriptionKey</DescriptionKey></GameModeType><GameModeType GameModeName="BOTW1v1Ghost200"><GameModeID>97</GameModeID><DisplayNameKey>GameModeType_BOTW1v1Ghost200_DisplayName</DisplayNameKey><Teams>false</Teams><MaxPlayers>2</MaxPlayers><Duration>480</Duration><StartingLives>3</StartingLives><ScoringType>STOCK</ScoringType><LevelSet>Standard1v1</LevelSet><DamageRatio>2</DamageRatio><GhostRule>true</GhostRule><DescriptionKey>GameModeType_BOTW1v1Ghost200_DescriptionKey</DescriptionKey></GameModeType><GameModeType GameModeName="BOTW2v2Ghost200"><GameModeID>98</GameModeID><DisplayNameKey>GameModeType_BOTW2v2Ghost200_DisplayName</DisplayNameKey><Teams>true</Teams><MaxPlayers>4</MaxPlayers><Duration>480</Duration><StartingLives>3</StartingLives><ScoringType>STOCK</ScoringType><LevelSet>Standard2v2</LevelSet><DamageRatio>2</DamageRatio><GhostRule>true</GhostRule><DescriptionKey>GameModeType_BOTW2v2Ghost200_DescriptionKey</DescriptionKey></GameModeType><GameModeType GameModeName="BOTW1v1Relay5"><GameModeID>99</GameModeID><DisplayNameKey>GameModeType_BOTW1v1Relay5_DisplayName</DisplayNameKey><Teams>false</Teams><MaxPlayers>2</MaxPlayers><Duration>480</Duration><StartingLives>5</StartingLives><ScoringType>RELAY</ScoringType><LevelSet>1v1StrikeoutBotW</LevelSet><DamageRatio>3</DamageRatio><DescriptionKey>GameModeType_BOTW1v1Relay5_DescriptionKey</DescriptionKey></GameModeType><GameModeType GameModeName="DefaultSoccer"><GameModeID>100</GameModeID><DisplayNameKey>GameModeType_DefaultSoccer_DisplayName</DisplayNameKey><Teams>TRUE</Teams><MaxPlayers>4</MaxPlayers><Duration>900</Duration><StartingLives>0</StartingLives><ScoringType>SOCCER</ScoringType><ScoreToWin>7</ScoreToWin><FixedCamera>true</FixedCamera><GadgetsOff>TRUE</GadgetsOff><TeamDamage>TRUE</TeamDamage></GameModeType><GameModeType GameModeName="BOTW2v2KungFoot"><GameModeID>101</GameModeID><DisplayNameKey>GameModeType_BOTW2v2KungFoot_DisplayName</DisplayNameKey><Teams>TRUE</Teams><MaxPlayers>4</MaxPlayers><Duration>300</Duration><StartingLives>0</StartingLives><ScoringType>SOCCER</ScoringType><ScoreToWin>5</ScoreToWin><FixedCamera>true</FixedCamera><LevelSet>SoccerAll</LevelSet><GadgetsOff>TRUE</GadgetsOff><TeamDamage>false</TeamDamage><DescriptionKey>GameModeType_BOTW2v2KungFoot_DescriptionKey</DescriptionKey></GameModeType><GameModeType GameModeName="BOTW3FFAGhost300"><GameModeID>102</GameModeID><DisplayNameKey>GameModeType_BOTW3FFAGhost300_DisplayName</DisplayNameKey><Teams>FALSE</Teams><MaxPlayers>3</MaxPlayers><Duration>180</Duration><StartingLives>0</StartingLives><ScoringType>TIMED</ScoringType><LevelSet>FFA3GhostBotW</LevelSet><DamageRatio>3</DamageRatio><GhostRule>true</GhostRule><DescriptionKey>GameModeType_BOTW3FFAGhost300_DescriptionKey</DescriptionKey></GameModeType><GameModeType GameModeName="DefaultHorde"><GameModeID>103</GameModeID><DisplayNameKey>GameModeType_DefaultHorde_DisplayName</DisplayNameKey><Teams>FALSE</Teams><MaxPlayers>4</MaxPlayers><Duration>900</Duration><StartingLives>0</StartingLives><ScoringType>HORDE</ScoringType><FixedCamera>TRUE</FixedCamera><LevelSet>HordeAll</LevelSet><DamageRatio>1</DamageRatio></GameModeType><GameModeType GameModeName="BOTWHorde"><GameModeID>104</GameModeID><DisplayNameKey>GameModeType_BOTWHorde_DisplayName</DisplayNameKey><Teams>FALSE</Teams><MaxPlayers>4</MaxPlayers><Duration>900</Duration><StartingLives>0</StartingLives><ScoringType>HORDE</ScoringType><FixedCamera>TRUE</FixedCamera><LevelSet>HordeAll</LevelSet><DamageRatio>1</DamageRatio><DescriptionKey>GameModeType_BOTWHorde_DescriptionKey</DescriptionKey></GameModeType><GameModeType GameModeName="DefaultBuddy"><GameModeID>105</GameModeID><DisplayNameKey>GameModeType_Buddy_DisplayName</DisplayNameKey><Teams>TRUE</Teams><MaxPlayers>2</MaxPlayers><Duration>240</Duration><StartingLives>0</StartingLives><ScoringType>BUDDY</ScoringType><LevelSet>BuddyAll</LevelSet></GameModeType><GameModeType GameModeName="BOTWBuddy"><GameModeID>106</GameModeID><DisplayNameKey>GameModeType_Buddy_DisplayName</DisplayNameKey><Teams>TRUE</Teams><MaxPlayers>2</MaxPlayers><Duration>180</Duration><StartingLives>0</StartingLives><ScoringType>BUDDY</ScoringType><LevelSet>BuddyBotW</LevelSet><DescriptionKey>GameModeType_BOTWBuddy_DescriptionKey</DescriptionKey></GameModeType><GameModeType GameModeName="DefaultRing"><GameModeID>107</GameModeID><DisplayNameKey>GameModeType_Ring_DisplayName</DisplayNameKey><Teams>FALSE</Teams><MaxPlayers>4</MaxPlayers><Duration>480</Duration><StartingLives>3</StartingLives><ScoringType>RING</ScoringType><LevelSet>RingAll</LevelSet></GameModeType><GameModeType GameModeName="BOTW2v2Ring"><GameModeID>108</GameModeID><DisplayNameKey>GameModeType_BOTWRing_DisplayName</DisplayNameKey><Teams>TRUE</Teams><MaxPlayers>4</MaxPlayers><Duration>480</Duration><StartingLives>3</StartingLives><ScoringType>RING</ScoringType><LevelSet>RingAll</LevelSet><DescriptionKey>GameModeType_BOTWRing_DescriptionKey</DescriptionKey></GameModeType></GameModeTypes>