<?xml version="1.0" encoding="UTF-8" standalone="yes"?><MissionTypes xmlns:xsi="http://www.w3.org/2001/XMLSchema-instance"><MissionType MissionName="--Template--"><MissionID>0</MissionID><Category>Weekly</Category><DescriptionKey>descriptionkey goes here. Must be a valid key in stringTable.xml</DescriptionKey><PrereqMissions>-----------</PrereqMissions><RewardGold>0</RewardGold><RewardPromoType>--</RewardPromoType><RewardMission>--</RewardMission><AutoStart>FALSE</AutoStart><CompleteAsBool>FALSE</CompleteAsBool><CompleteAtOnce>FALSE</CompleteAtOnce><SuccessCount>0</SuccessCount><Event1>--------------</Event1><Event2>--------------</Event2><Event3>--------------</Event3><Event4>--------------</Event4><Event5>--------------</Event5><Event6>--------------</Event6><Event7>--------------</Event7><Event8>--------------</Event8><Event9>--------------</Event9><Event10>--------------</Event10><Event11>--------------</Event11><Event12>--------------</Event12><Event13>--------------</Event13><MinimumTimeBetweenEvents>0</MinimumTimeBetweenEvents><NotForNewPlayers>false</NotForNewPlayers></MissionType><MissionType MissionName="KOsSwordAxe"><MissionID>1</MissionID><Category>Daily</Category><DescriptionKey>MissionType_KOsSwordAxe</DescriptionKey><RewardGold>250</RewardGold><SuccessCount>8</SuccessCount><Event1>itemKill.Sword</Event1><Event2>itemKill.Axe</Event2><Event3>itemKill.ThrowSword</Event3><Event4>itemKill.ThrowAxe</Event4></MissionType><MissionType MissionName="KOsPistolBow"><MissionID>2</MissionID><Category>Daily</Category><DescriptionKey>MissionType_KOsPistolBow</DescriptionKey><RewardGold>250</RewardGold><SuccessCount>8</SuccessCount><Event1>itemKill.Pistol</Event1><Event2>itemKill.Bow</Event2><Event3>itemKill.ThrowPistol</Event3><Event4>itemKill.ThrowBow</Event4></MissionType><MissionType MissionName="KOsCannonRocketLance"><MissionID>3</MissionID><Category>Daily</Category><DescriptionKey>MissionType_KOsCannonRocketLance</DescriptionKey><RewardGold>250</RewardGold><SuccessCount>8</SuccessCount><Event1>itemKill.Cannon</Event1><Event2>itemKill.RocketLance</Event2><Event3>itemKill.ThrowCannon</Event3><Event4>itemKill.ThrowLance</Event4></MissionType><MissionType MissionName="KOsHammerScythe"><MissionID>4</MissionID><Category>Daily</Category><DescriptionKey>MissionType_KOsHammerScythe</DescriptionKey><RewardGold>250</RewardGold><SuccessCount>8</SuccessCount><Event1>itemKill.Hammer</Event1><Event2>itemKill.Scythe</Event2><Event3>itemKill.ThrowHammer</Event3><Event4>itemKill.ThrowScythe</Event4></MissionType><MissionType MissionName="KOsRocketLanceKatar"><MissionID>5</MissionID><Category>Daily</Category><DescriptionKey>MissionType_KOsRocketLanceKatar</DescriptionKey><RewardGold>250</RewardGold><SuccessCount>8</SuccessCount><Event1>itemKill.RocketLance</Event1><Event2>itemKill.Katar</Event2><Event3>itemKill.ThrowLance</Event3><Event4>itemKill.ThrowKatar</Event4></MissionType><MissionType MissionName="KOsScythePistol"><MissionID>6</MissionID><Category>Daily</Category><DescriptionKey>MissionType_KOsScythePistol</DescriptionKey><RewardGold>250</RewardGold><SuccessCount>8</SuccessCount><Event1>itemKill.Scythe</Event1><Event2>itemKill.Pistol</Event2><Event3>itemKill.ThrowPistol</Event3><Event4>itemKill.ThrowScythe</Event4></MissionType><MissionType MissionName="KOsSpearSword"><MissionID>7</MissionID><Category>Daily</Category><DescriptionKey>MissionType_KOsSpearSword</DescriptionKey><RewardGold>250</RewardGold><SuccessCount>8</SuccessCount><Event1>itemKill.Spear</Event1><Event2>itemKill.Sword</Event2><Event3>itemKill.ThrowSword</Event3><Event4>itemKill.ThrowSpear</Event4></MissionType><MissionType MissionName="KOsOrbAxe"><MissionID>8</MissionID><Category>Daily</Category><DescriptionKey>MissionType_KOsOrbAxe</DescriptionKey><RewardGold>250</RewardGold><SuccessCount>8</SuccessCount><Event1>itemKill.Orb</Event1><Event2>itemKill.Axe</Event2><Event3>itemKill.ThrowAxe</Event3><Event4>itemKill.ThrowOrb</Event4></MissionType><MissionType MissionName="KOsFistsKatar"><MissionID>9</MissionID><Category>Daily</Category><DescriptionKey>MissionType_KOsFistsKatar</DescriptionKey><RewardGold>250</RewardGold><SuccessCount>8</SuccessCount><Event1>itemKill.Fists</Event1><Event2>itemKill.Katar</Event2><Event3>itemKill.ThrowKatar</Event3><Event4>itemKill.ThrowFists</Event4></MissionType><MissionType MissionName="KOsBowOrb"><MissionID>10</MissionID><Category>Daily</Category><DescriptionKey>MissionType_KOsBowOrb</DescriptionKey><RewardGold>250</RewardGold><SuccessCount>8</SuccessCount><Event1>itemKill.Bow</Event1><Event2>itemKill.Orb</Event2><Event3>itemKill.ThrowBow</Event3><Event4>itemKill.ThrowOrb</Event4></MissionType><MissionType MissionName="KOsHammerSpear"><MissionID>11</MissionID><Category>Daily</Category><DescriptionKey>MissionType_KOsHammerSpear</DescriptionKey><RewardGold>250</RewardGold><SuccessCount>8</SuccessCount><Event1>itemKill.Hammer</Event1><Event2>itemKill.Spear</Event2><Event3>itemKill.ThrowHammer</Event3><Event4>itemKill.ThrowSpear</Event4></MissionType><MissionType MissionName="KOsFistsCannon"><MissionID>12</MissionID><Category>Daily</Category><DescriptionKey>MissionType_KOsFistsCannon</DescriptionKey><RewardGold>250</RewardGold><SuccessCount>8</SuccessCount><Event1>itemKill.Fists</Event1><Event2>itemKill.Cannon</Event2><Event3>itemKill.ThrowCannon</Event3><Event4>itemKill.ThrowFists</Event4></MissionType><MissionType MissionName="PlayFreeForAll"><MissionID>13</MissionID><Category>Daily</Category><DescriptionKey>MissionType_PlayFreeForAll</DescriptionKey><RewardGold>250</RewardGold><SuccessCount>5</SuccessCount><Event1>playlistPlace.FreeForAll.1</Event1><Event2>playlistPlace.FreeForAll.2</Event2><Event3>playlistPlace.FreeForAll.3</Event3><Event4>playlistPlace.FreeForAll.4</Event4></MissionType><MissionType MissionName="Play2v2Unranked"><MissionID>14</MissionID><Category>Daily</Category><DescriptionKey>MissionType_Play2v2Unranked</DescriptionKey><RewardGold>250</RewardGold><SuccessCount>5</SuccessCount><Event1>playlistPlace.2v2Unranked.1</Event1><Event2>playlistPlace.2v2Unranked.2</Event2></MissionType><MissionType MissionName="Play2v2Ranked"><MissionID>15</MissionID><Category>Daily</Category><DescriptionKey>MissionType_Play2v2Ranked</DescriptionKey><RewardGold>250</RewardGold><SuccessCount>4</SuccessCount><Event1>playlistPlace.2v2Ranked.1</Event1><Event2>playlistPlace.2v2Ranked.2</Event2><NotForNewPlayers>true</NotForNewPlayers></MissionType><MissionType MissionName="Play1v1Experimental"><MissionID>16</MissionID><Category>Daily</Category><DescriptionKey>MissionType_Play1v1Experimental</DescriptionKey><RewardGold>250</RewardGold><SuccessCount>5</SuccessCount><Event1>playlistPlace.1v1Experimental.1</Event1><Event2>playlistPlace.1v1Experimental.2</Event2></MissionType><MissionType MissionName="Play1v1Ranked"><MissionID>17</MissionID><Category>Daily</Category><DescriptionKey>MissionType_Play1v1Ranked</DescriptionKey><RewardGold>250</RewardGold><SuccessCount>5</SuccessCount><Event1>playlistPlace.1v1Ranked.1</Event1><Event2>playlistPlace.1v1Ranked.2</Event2><NotForNewPlayers>true</NotForNewPlayers></MissionType><MissionType MissionName="Play1v1RelayUnranked"><MissionID>18</MissionID><Category>Daily</Category><DescriptionKey>MissionType_Play1v1RelayUnranked</DescriptionKey><RewardGold>250</RewardGold><SuccessCount>5</SuccessCount><Event1>playlistPlace.1v1RelayUnranked.1</Event1><Event2>playlistPlace.1v1RelayUnranked.2</Event2></MissionType><MissionType MissionName="WinsFreeForAll"><MissionID>19</MissionID><Category>Daily</Category><DescriptionKey>MissionType_WinsFreeForAll</DescriptionKey><RewardGold>250</RewardGold><SuccessCount>3</SuccessCount><Event1>playlistPlace.FreeForAll.1</Event1><Event1>playlistPlace.FreeForAll.2</Event1></MissionType><MissionType MissionName="Wins2v2Unranked"><MissionID>20</MissionID><Category>Daily</Category><DescriptionKey>MissionType_Wins2v2Unranked</DescriptionKey><RewardGold>250</RewardGold><SuccessCount>3</SuccessCount><Event1>playlistPlace.2v2Unranked.1</Event1></MissionType><MissionType MissionName="Wins2v2Ranked"><MissionID>21</MissionID><Category>Daily</Category><DescriptionKey>MissionType_Wins2v2Ranked</DescriptionKey><RewardGold>250</RewardGold><SuccessCount>2</SuccessCount><Event1>playlistPlace.2v2Ranked.1</Event1><NotForNewPlayers>true</NotForNewPlayers></MissionType><MissionType MissionName="Wins1v1Experimental"><MissionID>22</MissionID><Category>Daily</Category><DescriptionKey>MissionType_Wins1v1Experimental</DescriptionKey><RewardGold>250</RewardGold><SuccessCount>3</SuccessCount><Event1>playlistPlace.1v1Experimental.1</Event1></MissionType><MissionType MissionName="Wins1v1Ranked"><MissionID>23</MissionID><Category>Daily</Category><DescriptionKey>MissionType_Wins1v1Ranked</DescriptionKey><RewardGold>250</RewardGold><SuccessCount>3</SuccessCount><Event1>playlistPlace.1v1Ranked.1</Event1><NotForNewPlayers>true</NotForNewPlayers></MissionType><MissionType MissionName="Wins1v1RelayUnranked"><MissionID>24</MissionID><Category>Daily</Category><DescriptionKey>MissionType_Wins1v1RelayUnranked</DescriptionKey><RewardGold>250</RewardGold><SuccessCount>3</SuccessCount><Event1>playlistPlace.1v1RelayUnranked.1</Event1></MissionType><MissionType MissionName="KOs"><MissionID>25</MissionID><Category>Daily</Category><DescriptionKey>MissionType_KOs</DescriptionKey><RewardGold>250</RewardGold><SuccessCount>25</SuccessCount><Event1>kill</Event1></MissionType><MissionType MissionName="GravityCancelHits"><MissionID>26</MissionID><Category>Daily</Category><DescriptionKey>MissionType_GravityCancelHits</DescriptionKey><RewardGold>250</RewardGold><SuccessCount>10</SuccessCount><Event1>hit.GravityCancel</Event1><NotForNewPlayers>true</NotForNewPlayers></MissionType><MissionType MissionName="DailyLogin1"><MissionID>29</MissionID><Category>DailyLogin</Category><RewardGold>50</RewardGold><AutoStart>TRUE</AutoStart><CompleteAsBool>TRUE</CompleteAsBool><SuccessCount>1</SuccessCount><Event1>login.1</Event1></MissionType><MissionType MissionName="DailyLogin2"><MissionID>30</MissionID><Category>DailyLogin</Category><RewardGold>100</RewardGold><AutoStart>TRUE</AutoStart><CompleteAsBool>TRUE</CompleteAsBool><SuccessCount>1</SuccessCount><Event1>login.2</Event1></MissionType><MissionType MissionName="DailyLogin3"><MissionID>31</MissionID><Category>DailyLogin</Category><RewardGold>150</RewardGold><AutoStart>TRUE</AutoStart><CompleteAsBool>TRUE</CompleteAsBool><SuccessCount>1</SuccessCount><Event1>login.3</Event1></MissionType><MissionType MissionName="DailyLogin4"><MissionID>32</MissionID><Category>DailyLogin</Category><RewardGold>200</RewardGold><AutoStart>TRUE</AutoStart><CompleteAsBool>TRUE</CompleteAsBool><SuccessCount>1</SuccessCount><Event1>login.4</Event1></MissionType><MissionType MissionName="DailyLogin5"><MissionID>33</MissionID><Category>DailyLogin</Category><RewardGold>250</RewardGold><AutoStart>TRUE</AutoStart><CompleteAsBool>TRUE</CompleteAsBool><SuccessCount>1</SuccessCount><Event1>login.5</Event1></MissionType><MissionType MissionName="DailyLogin6"><MissionID>34</MissionID><Category>DailyLogin</Category><RewardGold>0</RewardGold><AutoStart>FALSE</AutoStart><CompleteAsBool>TRUE</CompleteAsBool><SuccessCount>1</SuccessCount><Event1>login.6</Event1></MissionType><MissionType MissionName="DailyLogin7"><MissionID>35</MissionID><Category>DailyLogin</Category><RewardGold>0</RewardGold><AutoStart>FALSE</AutoStart><CompleteAsBool>TRUE</CompleteAsBool><SuccessCount>1</SuccessCount><Event1>login.7</Event1></MissionType><MissionType MissionName="KOsSwordHammer"><MissionID>36</MissionID><Category>Daily</Category><DescriptionKey>MissionType_KOsSwordHammer</DescriptionKey><RewardGold>250</RewardGold><SuccessCount>8</SuccessCount><Event1>itemKill.Sword</Event1><Event2>itemKill.Hammer</Event2><Event3>itemKill.ThrowSword</Event3><Event4>itemKill.ThrowHammer</Event4></MissionType><MissionType MissionName="KOsPistolFists"><MissionID>37</MissionID><Category>Daily</Category><DescriptionKey>MissionType_KOsPistolFists</DescriptionKey><RewardGold>250</RewardGold><SuccessCount>8</SuccessCount><Event1>itemKill.Pistol</Event1><Event2>itemKill.Fists</Event2><Event3>itemKill.ThrowPistol</Event3><Event4>itemKill.ThrowFists</Event4></MissionType><MissionType MissionName="KOsCannonAxe"><MissionID>38</MissionID><Category>Daily</Category><DescriptionKey>MissionType_KOsCannonAxe</DescriptionKey><RewardGold>250</RewardGold><SuccessCount>8</SuccessCount><Event1>itemKill.Cannon</Event1><Event2>itemKill.Axe</Event2><Event3>itemKill.ThrowAxe</Event3><Event4>itemKill.ThrowCannon</Event4></MissionType><MissionType MissionName="KOsBowScythe"><MissionID>39</MissionID><Category>Daily</Category><DescriptionKey>MissionType_KOsBowScythe</DescriptionKey><RewardGold>250</RewardGold><SuccessCount>8</SuccessCount><Event1>itemKill.Bow</Event1><Event2>itemKill.Scythe</Event2><Event3>itemKill.ThrowBow</Event3><Event4>itemKill.ThrowScythe</Event4></MissionType><MissionType MissionName="KOsRocketLanceSpear"><MissionID>40</MissionID><Category>Daily</Category><DescriptionKey>MissionType_KOsRocketLanceSpear</DescriptionKey><RewardGold>250</RewardGold><SuccessCount>8</SuccessCount><Event1>itemKill.RocketLance</Event1><Event2>itemKill.Spear</Event2><Event3>itemKill.ThrowLance</Event3><Event4>itemKill.ThrowSpear</Event4></MissionType><MissionType MissionName="KOsOrbKatar"><MissionID>41</MissionID><Category>Daily</Category><DescriptionKey>MissionType_KOsOrbKatar</DescriptionKey><RewardGold>250</RewardGold><SuccessCount>8</SuccessCount><Event1>itemKill.Orb</Event1><Event2>itemKill.Katar</Event2><Event3>itemKill.ThrowKatar</Event3><Event4>itemKill.ThrowOrb</Event4></MissionType><MissionType MissionName="KOsUnarmed"><MissionID>42</MissionID><Category>Daily</Category><DescriptionKey>MissionType_KOsUnarmed</DescriptionKey><RewardGold>250</RewardGold><SuccessCount>6</SuccessCount><Event1>itemKill.Unarmed</Event1></MissionType><MissionType MissionName="KOsGadgets"><MissionID>43</MissionID><Category>Daily</Category><DescriptionKey>MissionType_KOsGadgets</DescriptionKey><RewardGold>250</RewardGold><SuccessCount>3</SuccessCount><Event1>itemKill.BouncyBomb</Event1><Event2>itemKill.ProxMine</Event2><Event3>itemKill.SpikeBall</Event3><Event4>itemKill.SpawnBotFlyby</Event4></MissionType><MissionType MissionName="KOsThrownWeapons"><MissionID>44</MissionID><Category>Daily</Category><DescriptionKey>MissionType_KOsThrownWeapons</DescriptionKey><RewardGold>250</RewardGold><SuccessCount>3</SuccessCount><Event1>itemKill.ThrowSword</Event1><Event2>itemKill.ThrowHammer</Event2><Event3>itemKill.ThrowPistol</Event3><Event4>itemKill.ThrowLance</Event4><Event5>itemKill.ThrowSpear</Event5><Event6>itemKill.ThrowKatar</Event6><Event7>itemKill.ThrowAxe</Event7><Event8>itemKill.ThrowBow</Event8><Event9>itemKill.ThrowFists</Event9><Event10>itemKill.ThrowScythe</Event10><Event11>itemKill.ThrowCannon</Event11><Event12>itemKill.ThrowOrb</Event12></MissionType><MissionType MissionName="BOTWWinOneBonus"><MissionID>47</MissionID><Category>Weekly</Category><DescriptionKey>MissionType_BOTWWinOneBonus_DescriptionKey</DescriptionKey><RewardGold>300</RewardGold><AutoStart>false</AutoStart><CompleteAsBool>False</CompleteAsBool><SuccessCount>1</SuccessCount><Event1>playlistPlace.BOTW3v3.1</Event1><Event2>playlistPlace.BOTW2v2Relay.1</Event2><Event3>playlistPlace.BOTW2v2Ghost200.1</Event3><Event4>playlistPlace.BOTW3FFA.1</Event4><Event5>playlistPlace.BOTW3v3Beachbrawl.1</Event5><Event6>playlistPlace.BOTWHeatwaveSnowbrawl.1</Event6><Event7>playlistPlace.BOTW2v2Switch.1</Event7><Event8>playlistPlace.BOTW2v2Snowbrawl.1</Event8><Event9>playlistPlace.BOTW3FFAGhost300.1</Event9></MissionType><MissionType MissionName="BOTWWinTwoBonus"><MissionID>47</MissionID><Category>Weekly</Category><DescriptionKey>MissionType_BOTWWinTwoBonus_DescriptionKey</DescriptionKey><RewardGold>300</RewardGold><AutoStart>True</AutoStart><CompleteAsBool>False</CompleteAsBool><SuccessCount>2</SuccessCount><Event1>playlistPlace.BOTW1v1Ghost200.1</Event1><Event2>playlistPlace.BOTW3v3Brawlball.1</Event2><Event3>playlistPlace.BOTW1v1300.1</Event3><Event4>playlistPlace.BOTW1v1Relay5.1</Event4><Event5>playlistPlace.BOTW2v2KungFoot.1</Event5><Event6>playlistPlace.BOTWBuddy.1</Event6><Event7>playlistPlace.BOTW2v2Ring.1</Event7></MissionType><MissionType MissionName="BOTW1stOr2ndOneBonus"><MissionID>47</MissionID><Category>Weekly</Category><DescriptionKey>MissionType_BOTW1stOr2ndOneBonus_DescriptionKey</DescriptionKey><RewardGold>300</RewardGold><AutoStart>false</AutoStart><CompleteAsBool>False</CompleteAsBool><SuccessCount>1</SuccessCount><Event1>playlistPlace.BOTWHeatwaveFFA.1</Event1><Event2>playlistPlace.BOTWHeatwaveFFA.2</Event2><Event3>playlistPlace.BOTWPlatformFight.1</Event3><Event4>playlistPlace.BOTWPlatformFight.2</Event4><Event5>playlistPlace.BOTWSnowbrawl.1</Event5><Event6>playlistPlace.BOTWSnowbrawl.2</Event6><Event7>playlistPlace.BOTWHorde.1</Event7><Event8>playlistPlace.BOTWHorde.2</Event8></MissionType><MissionType MissionName="GameFuel"><MissionID>48</MissionID><Category>LimitedTime</Category><RewardPromoType>Soda</RewardPromoType><SuccessCount>10000</SuccessCount><Event1>gainXp</Event1></MissionType><MissionType MissionName="WinsSwordUser"><MissionID>49</MissionID><Category>Daily</Category><DescriptionKey>MissionType_WinsSwordUser</DescriptionKey><RewardGold>250</RewardGold><SuccessCount>3</SuccessCount><Event1>heroPlace.SwordUser.1</Event1><MinimumTimeBetweenEvents>60</MinimumTimeBetweenEvents></MissionType><MissionType MissionName="WinsHammerUser"><MissionID>50</MissionID><Category>Daily</Category><DescriptionKey>MissionType_WinsHammerUser</DescriptionKey><RewardGold>250</RewardGold><SuccessCount>3</SuccessCount><Event1>heroPlace.HammerUser.1</Event1><MinimumTimeBetweenEvents>60</MinimumTimeBetweenEvents></MissionType><MissionType MissionName="WinsPistolUser"><MissionID>51</MissionID><Category>Daily</Category><DescriptionKey>MissionType_WinsPistolUser</DescriptionKey><RewardGold>250</RewardGold><SuccessCount>3</SuccessCount><Event1>heroPlace.PistolUser.1</Event1><MinimumTimeBetweenEvents>60</MinimumTimeBetweenEvents></MissionType><MissionType MissionName="WinsLanceUser"><MissionID>52</MissionID><Category>Daily</Category><DescriptionKey>MissionType_WinsLanceUser</DescriptionKey><RewardGold>250</RewardGold><SuccessCount>3</SuccessCount><Event1>heroPlace.LanceUser.1</Event1><MinimumTimeBetweenEvents>60</MinimumTimeBetweenEvents></MissionType><MissionType MissionName="WinsSpearUser"><MissionID>53</MissionID><Category>Daily</Category><DescriptionKey>MissionType_WinsSpearUser</DescriptionKey><RewardGold>250</RewardGold><SuccessCount>3</SuccessCount><Event1>heroPlace.SpearUser.1</Event1><MinimumTimeBetweenEvents>60</MinimumTimeBetweenEvents></MissionType><MissionType MissionName="WinsKatarUser"><MissionID>54</MissionID><Category>Daily</Category><DescriptionKey>MissionType_WinsKatarUser</DescriptionKey><RewardGold>250</RewardGold><SuccessCount>3</SuccessCount><Event1>heroPlace.KatarUser.1</Event1><MinimumTimeBetweenEvents>60</MinimumTimeBetweenEvents></MissionType><MissionType MissionName="WinsAxeUser"><MissionID>55</MissionID><Category>Daily</Category><DescriptionKey>MissionType_WinsAxeUser</DescriptionKey><RewardGold>250</RewardGold><SuccessCount>3</SuccessCount><Event1>heroPlace.AxeUser.1</Event1><MinimumTimeBetweenEvents>60</MinimumTimeBetweenEvents></MissionType><MissionType MissionName="WinsBowUser"><MissionID>56</MissionID><Category>Daily</Category><DescriptionKey>MissionType_WinsBowUser</DescriptionKey><RewardGold>250</RewardGold><SuccessCount>3</SuccessCount><Event1>heroPlace.BowUser.1</Event1><MinimumTimeBetweenEvents>60</MinimumTimeBetweenEvents></MissionType><MissionType MissionName="WinsFistsUser"><MissionID>57</MissionID><Category>Daily</Category><DescriptionKey>MissionType_WinsFistsUser</DescriptionKey><RewardGold>250</RewardGold><SuccessCount>3</SuccessCount><Event1>heroPlace.FistsUser.1</Event1><MinimumTimeBetweenEvents>60</MinimumTimeBetweenEvents></MissionType><MissionType MissionName="WinsScytheUser"><MissionID>58</MissionID><Category>Daily</Category><DescriptionKey>MissionType_WinsScytheUser</DescriptionKey><RewardGold>250</RewardGold><SuccessCount>3</SuccessCount><Event1>heroPlace.ScytheUser.1</Event1><MinimumTimeBetweenEvents>60</MinimumTimeBetweenEvents></MissionType><MissionType MissionName="WinsCannonUser"><MissionID>59</MissionID><Category>Daily</Category><DescriptionKey>MissionType_WinsCannonUser</DescriptionKey><RewardGold>250</RewardGold><SuccessCount>3</SuccessCount><Event1>heroPlace.CannonUser.1</Event1><MinimumTimeBetweenEvents>60</MinimumTimeBetweenEvents></MissionType><MissionType MissionName="WinsOrbUser"><MissionID>60</MissionID><Category>Daily</Category><DescriptionKey>MissionType_WinsOrbUser</DescriptionKey><RewardGold>250</RewardGold><SuccessCount>3</SuccessCount><Event1>heroPlace.OrbUser.1</Event1><MinimumTimeBetweenEvents>60</MinimumTimeBetweenEvents></MissionType></MissionTypes>